django_wools/__init__.py
django_wools/_google_fonts.py
django_wools/db.py
django_wools/fonts.py
django_wools/forms.py
django_wools/management/commands/wools_import_fonts.py
django_wools/middlewares.py
django_wools/settings.py
django_wools/settings_types.py
django_wools/storage.py
django_wools/templates/wools/fonts.html
django_wools/templates/wools/images/fixed_size.html
django_wools/templatetags/wools_fonts.py
django_wools/templatetags/wools_for_wt_images.py
django_wools/templatetags/wools_utils.py
django_wools-0.2.1.dist-info/WHEEL
django_wools-0.2.1.dist-info/METADATA
django_wools-0.2.1.dist-info/RECORD
