Metadata-Version: 2.1
Name: django-wools
Version: 0.2.1
Summary: Django tools from WITH
Home-page: https://github.com/WithIO/django-wools
License: WTFPL
Author: Rémy Sanchez
Author-email: remy.sanchez@with-madrid.com
Requires-Python: >=3.6,<4.0
Classifier: License :: Other/Proprietary License
Classifier: Programming Language :: Python :: 3
Classifier: Programming Language :: Python :: 3.6
Classifier: Programming Language :: Python :: 3.7
Classifier: Programming Language :: Python :: 3.8
Classifier: Programming Language :: Python :: 3.9
Classifier: Programming Language :: Python :: 3.10
Classifier: Programming Language :: Python :: 3.11
Requires-Dist: django (>1.7.0)
Requires-Dist: fonttools[woff] (>=4.21.1,<5.0.0)
Requires-Dist: httpx (<2.0.0)
Requires-Dist: minify-html (>0.7.2)
Requires-Dist: psutil (>2.0.0)
Requires-Dist: tqdm (>3.0.0)
Requires-Dist: zopflipy (>1.1)
Project-URL: Repository, https://github.com/WithIO/django-wools
